snob_lib-0.1.0.dist-info/METADATA
snob_lib-0.1.0.dist-info/WHEEL
snob_lib-0.1.0.dist-info/licenses/LICENSE
snob_lib.libs/libgcc_s-b5472b99.so.1
snob_lib/__init__.py
snob_lib/snob_lib.pypy39-pp73-x86-linux-gnu.so
snob_lib-0.1.0.dist-info/RECORD
