Metadata-Version: 2.4
Name: snob_lib
Version: 0.1.0
Classifier: Programming Language :: Rust
Classifier: Programming Language :: Python :: Implementation :: CPython
Classifier: Programming Language :: Python :: Implementation :: PyPy
License-File: LICENSE
Summary: A tool that only selects meaningful python tests to run.
Keywords: snob,pytest,testing,rust,rts,maturin,pyo3
Home-Page: https://github.com/alexpasmantier/snob
Author: Alexandre Pasmantier <alex.pasmant@gmail.com>, Bertrand Chardon <bertrand.chardon@gmail.com>
Author-email: Bertrand Chardon <bertrand.chardon@gmail.com>, Alexandre Pasmantier <alex.pasmant@gmail.com>
License: MIT
Requires-Python: >=3.8
Project-URL: Homepage, https://github.com/alexpasmantier/snob
